LICENSE.md
MANIFEST.in
README.md
setup.py
GangliPy.egg-info/PKG-INFO
GangliPy.egg-info/SOURCES.txt
GangliPy.egg-info/dependency_links.txt
GangliPy.egg-info/top_level.txt
examples/__init__.py
ganglipy/__init__.py
ganglipy/datasets/__init__.py
ganglipy/datasets/unifoundry.py
ganglipy/encoder/__init__.py
ganglipy/encoder/encoder.py
ganglipy/sparse/__init__.py
ganglipy/sparse/boosting.py
ganglipy/sparse/kwinners.py
ganglipy/sparse/kwinners_boosted.py
ganglipy/sparse/lateral_inhibition.py
ganglipy/sparse/sparse_variational_pooler.py
tests/__init__.py